mypackcrazyj/__init__.py
mypackcrazyj/text.py
mypackcrazyj-0.1.1.dist-info/LICENSE
mypackcrazyj-0.1.1.dist-info/METADATA
mypackcrazyj-0.1.1.dist-info/WHEEL
mypackcrazyj-0.1.1.dist-info/top_level.txt
mypackcrazyj-0.1.1.dist-info/RECORD
