Metadata-Version: 2.1
Name: mypackcrazyj
Version: 0.1.1
Summary: package testing
Home-page: http://github.com/crazyj7/python/mypack_crazyj
Author: crazyj
Author-email: crazyj7@gmail.com
License: MIT
Platform: UNKNOWN
Requires-Dist: markdown
